pyn5-1.1.1.dist-info/METADATA
pyn5-1.1.1.dist-info/WHEEL
pyn5/file_group.py
pyn5/common.py
pyn5/dataset.py
pyn5/__init__.py
pyn5/python_wrappers.py
pyn5/attributes.py
pyn5/pyn5.cpython-36m-x86_64-linux-gnu.so
pyn5-1.1.1.dist-info/RECORD
