Metadata-Version: 2.1
Name: pyn5
Version: 1.1.1
Classifier: Development Status :: 2 - Pre-Alpha
Classifier: Intended Audience :: Developers
Classifier: License :: OSI Approved :: MIT License
Classifier: Natural Language :: English
Classifier: Programming Language :: Rust
Classifier: Programming Language :: Python :: 3.6
Classifier: Programming Language :: Python :: 3.7
Classifier: Programming Language :: Python :: 3.8
Requires-Dist: numpy
Requires-Dist: h5py_like>=0.6.0
Summary: Python wrapper around rust-n5.
Home-Page: https://github.com/pattonw/rust-pyn5
Author: pattonw <pattonw@hhmi.org>
Author-Email: pattonw <pattonw@hhmi.org>
License: MIT
Requires-Python: >=3.6
